{
  "int": null,
  "note": null,
  "scheda": null,
  "enti": {
    "ente_p": {
      "desc": "CAGLIARI",
      "cod": 17,
      "ele_m": 0,
      "ele_f": 0,
      "ele_t": 453839,
      "com": [
        {
          "cod_reg": 20,
          "com_att": 3,
          "num_com": 4
        }
      ],
      "com_vot": null
    },
    "enti_f": [
      {
        "tipo": "COMUNE",
        "desc": "ARMUNGIA",
        "cod": 21,
        "ele_m": 0,
        "ele_f": 0,
        "ele_t": 358,
        "tipo_tras": "SZ",
        "com_vot": null
      },
      {
        "tipo": "COMUNE",
        "desc": "ASSEMINI",
        "cod": 30,
        "ele_m": 0,
        "ele_f": 0,
        "ele_t": 21739,
        "tipo_tras": "SZ",
        "com_vot": null
      },
      {
        "tipo": "COMUNE",
        "desc": "BALLAO",
        "cod": 41,
        "ele_m": 0,
        "ele_f": 0,
        "ele_t": 632,
        "tipo_tras": "SZ",
        "com_vot": null
      },
      {
        "tipo": "COMUNE",
        "desc": "BARRALI",
        "cod": 51,
        "ele_m": 0,
        "ele_f": 0,
        "ele_t": 937,
        "tipo_tras": "SZ",
        "com_vot": null
      },
      {
        "tipo": "COMUNE",
        "desc": "BURCEI",
        "cod": 81,
        "ele_m": 0,
        "ele_f": 0,
        "ele_t": 2181,
        "tipo_tras": "SZ",
        "com_vot": null
      },
      {
        "tipo": "COMUNE",
        "desc": "CAGLIARI",
        "cod": 90,
        "ele_m": 0,
        "ele_f": 0,
        "ele_t": 122812,
        "tipo_tras": "SZ",
        "com_vot": null
      },
      {
        "tipo": "COMUNE",
        "desc": "CAPOTERRA",
        "cod": 110,
        "ele_m": 0,
        "ele_f": 0,
        "ele_t": 19472,
        "tipo_tras": "SZ",
        "com_vot": null
      },
      {
        "tipo": "COMUNE",
        "desc": "CASTIADAS",
        "cod": 132,
        "ele_m": 0,
        "ele_f": 0,
        "ele_t": 1473,
        "tipo_tras": "SZ",
        "com_vot": null
      },
      {
        "tipo": "COMUNE",
        "desc": "DECIMOMANNU",
        "cod": 150,
        "ele_m": 0,
        "ele_f": 0,
        "ele_t": 7054,
        "tipo_tras": "SZ",
        "com_vot": null
      },
      {
        "tipo": "COMUNE",
        "desc": "DECIMOPUTZU",
        "cod": 161,
        "ele_m": 0,
        "ele_f": 0,
        "ele_t": 3422,
        "tipo_tras": "SZ",
        "com_vot": null
      },
      {
        "tipo": "COMUNE",
        "desc": "DOLIANOVA",
        "cod": 171,
        "ele_m": 0,
        "ele_f": 0,
        "ele_t": 8006,
        "tipo_tras": "SZ",
        "com_vot": null
      },
      {
        "tipo": "COMUNE",
        "desc": "DOMUS DE MARIA",
        "cod": 181,
        "ele_m": 0,
        "ele_f": 0,
        "ele_t": 1431,
        "tipo_tras": "SZ",
        "com_vot": null
      },
      {
        "tipo": "COMUNE",
        "desc": "DONORI",
        "cod": 199,
        "ele_m": 0,
        "ele_f": 0,
        "ele_t": 1670,
        "tipo_tras": "SZ",
        "com_vot": null
      },
      {
        "tipo": "COMUNE",
        "desc": "ELMAS",
        "cod": 201,
        "ele_m": 0,
        "ele_f": 0,
        "ele_t": 7915,
        "tipo_tras": "SZ",
        "com_vot": null
      },
      {
        "tipo": "COMUNE",
        "desc": "ESCALAPLANO",
        "cod": 214,
        "ele_m": 0,
        "ele_f": 0,
        "ele_t": 1733,
        "tipo_tras": "SZ",
        "com_vot": null
      },
      {
        "tipo": "COMUNE",
        "desc": "ESCOLCA",
        "cod": 215,
        "ele_m": 0,
        "ele_f": 0,
        "ele_t": 471,
        "tipo_tras": "SZ",
        "com_vot": null
      },
      {
        "tipo": "COMUNE",
        "desc": "ESTERZILI",
        "cod": 219,
        "ele_m": 0,
        "ele_f": 0,
        "ele_t": 491,
        "tipo_tras": "SZ",
        "com_vot": null
      },
      {
        "tipo": "COMUNE",
        "desc": "GENONI",
        "cod": 222,
        "ele_m": 0,
        "ele_f": 0,
        "ele_t": 630,
        "tipo_tras": "SZ",
        "com_vot": null
      },
      {
        "tipo": "COMUNE",
        "desc": "GERGEI",
        "cod": 236,
        "ele_m": 0,
        "ele_f": 0,
        "ele_t": 951,
        "tipo_tras": "SZ",
        "com_vot": null
      },
      {
        "tipo": "COMUNE",
        "desc": "GESICO",
        "cod": 241,
        "ele_m": 0,
        "ele_f": 0,
        "ele_t": 613,
        "tipo_tras": "SZ",
        "com_vot": null
      },
      {
        "tipo": "COMUNE",
        "desc": "GONI",
        "cod": 271,
        "ele_m": 0,
        "ele_f": 0,
        "ele_t": 388,
        "tipo_tras": "SZ",
        "com_vot": null
      },
      {
        "tipo": "COMUNE",
        "desc": "GUAMAGGIORE",
        "cod": 301,
        "ele_m": 0,
        "ele_f": 0,
        "ele_t": 755,
        "tipo_tras": "SZ",
        "com_vot": null
      },
      {
        "tipo": "COMUNE",
        "desc": "GUASILA",
        "cod": 311,
        "ele_m": 0,
        "ele_f": 0,
        "ele_t": 2066,
        "tipo_tras": "SZ",
        "com_vot": null
      },
      {
        "tipo": "COMUNE",
        "desc": "ISILI",
        "cod": 317,
        "ele_m": 0,
        "ele_f": 0,
        "ele_t": 2054,
        "tipo_tras": "SZ",
        "com_vot": null
      },
      {
        "tipo": "COMUNE",
        "desc": "MANDAS",
        "cod": 361,
        "ele_m": 0,
        "ele_f": 0,
        "ele_t": 1683,
        "tipo_tras": "SZ",
        "com_vot": null
      },
      {
        "tipo": "COMUNE",
        "desc": "MARACALAGONIS",
        "cod": 370,
        "ele_m": 0,
        "ele_f": 0,
        "ele_t": 6701,
        "tipo_tras": "SZ",
        "com_vot": null
      },
      {
        "tipo": "COMUNE",
        "desc": "MONASTIR",
        "cod": 379,
        "ele_m": 0,
        "ele_f": 0,
        "ele_t": 3746,
        "tipo_tras": "SZ",
        "com_vot": null
      },
      {
        "tipo": "COMUNE",
        "desc": "MONSERRATO",
        "cod": 381,
        "ele_m": 0,
        "ele_f": 0,
        "ele_t": 16235,
        "tipo_tras": "SZ",
        "com_vot": null
      },
      {
        "tipo": "COMUNE",
        "desc": "MURAVERA",
        "cod": 391,
        "ele_m": 0,
        "ele_f": 0,
        "ele_t": 4336,
        "tipo_tras": "SZ",
        "com_vot": null
      },
      {
        "tipo": "COMUNE",
        "desc": "NURAGUS",
        "cod": 395,
        "ele_m": 0,
        "ele_f": 0,
        "ele_t": 697,
        "tipo_tras": "SZ",
        "com_vot": null
      },
      {
        "tipo": "COMUNE",
        "desc": "NURALLAO",
        "cod": 398,
        "ele_m": 0,
        "ele_f": 0,
        "ele_t": 981,
        "tipo_tras": "SZ",
        "com_vot": null
      },
      {
        "tipo": "COMUNE",
        "desc": "NURAMINIS",
        "cod": 421,
        "ele_m": 0,
        "ele_f": 0,
        "ele_t": 2035,
        "tipo_tras": "SZ",
        "com_vot": null
      },
      {
        "tipo": "COMUNE",
        "desc": "NURRI",
        "cod": 425,
        "ele_m": 0,
        "ele_f": 0,
        "ele_t": 1699,
        "tipo_tras": "SZ",
        "com_vot": null
      },
      {
        "tipo": "COMUNE",
        "desc": "ORROLI",
        "cod": 428,
        "ele_m": 0,
        "ele_f": 0,
        "ele_t": 1695,
        "tipo_tras": "SZ",
        "com_vot": null
      },
      {
        "tipo": "COMUNE",
        "desc": "ORTACESUS",
        "cod": 441,
        "ele_m": 0,
        "ele_f": 0,
        "ele_t": 712,
        "tipo_tras": "SZ",
        "com_vot": null
      },
      {
        "tipo": "COMUNE",
        "desc": "PIMENTEL",
        "cod": 479,
        "ele_m": 0,
        "ele_f": 0,
        "ele_t": 926,
        "tipo_tras": "SZ",
        "com_vot": null
      },
      {
        "tipo": "COMUNE",
        "desc": "PULA",
        "cod": 500,
        "ele_m": 0,
        "ele_f": 0,
        "ele_t": 6057,
        "tipo_tras": "SZ",
        "com_vot": null
      },
      {
        "tipo": "COMUNE",
        "desc": "QUARTU SANT'ELENA",
        "cod": 510,
        "ele_m": 0,
        "ele_f": 0,
        "ele_t": 58000,
        "tipo_tras": "SZ",
        "com_vot": null
      },
      {
        "tipo": "COMUNE",
        "desc": "QUARTUCCIU",
        "cod": 501,
        "ele_m": 0,
        "ele_f": 0,
        "ele_t": 10870,
        "tipo_tras": "SZ",
        "com_vot": null
      },
      {
        "tipo": "COMUNE",
        "desc": "SADALI",
        "cod": 517,
        "ele_m": 0,
        "ele_f": 0,
        "ele_t": 666,
        "tipo_tras": "SZ",
        "com_vot": null
      },
      {
        "tipo": "COMUNE",
        "desc": "SAMATZAI",
        "cod": 531,
        "ele_m": 0,
        "ele_f": 0,
        "ele_t": 1294,
        "tipo_tras": "SZ",
        "com_vot": null
      },
      {
        "tipo": "COMUNE",
        "desc": "SAN BASILIO",
        "cod": 541,
        "ele_m": 0,
        "ele_f": 0,
        "ele_t": 916,
        "tipo_tras": "SZ",
        "com_vot": null
      },
      {
        "tipo": "COMUNE",
        "desc": "SAN NICOLO' GERREI",
        "cod": 581,
        "ele_m": 0,
        "ele_f": 0,
        "ele_t": 625,
        "tipo_tras": "SZ",
        "com_vot": null
      },
      {
        "tipo": "COMUNE",
        "desc": "SAN SPERATE",
        "cod": 591,
        "ele_m": 0,
        "ele_f": 0,
        "ele_t": 7275,
        "tipo_tras": "SZ",
        "com_vot": null
      },
      {
        "tipo": "COMUNE",
        "desc": "SAN VITO",
        "cod": 641,
        "ele_m": 0,
        "ele_f": 0,
        "ele_t": 2953,
        "tipo_tras": "SZ",
        "com_vot": null
      },
      {
        "tipo": "COMUNE",
        "desc": "SANT'ANDREA FRIUS",
        "cod": 645,
        "ele_m": 0,
        "ele_f": 0,
        "ele_t": 1425,
        "tipo_tras": "SZ",
        "com_vot": null
      },
      {
        "tipo": "COMUNE",
        "desc": "SARROCH",
        "cod": 660,
        "ele_m": 0,
        "ele_f": 0,
        "ele_t": 4336,
        "tipo_tras": "SZ",
        "com_vot": null
      },
      {
        "tipo": "COMUNE",
        "desc": "SELARGIUS",
        "cod": 680,
        "ele_m": 0,
        "ele_f": 0,
        "ele_t": 24317,
        "tipo_tras": "SZ",
        "com_vot": null
      },
      {
        "tipo": "COMUNE",
        "desc": "SELEGAS",
        "cod": 691,
        "ele_m": 0,
        "ele_f": 0,
        "ele_t": 1100,
        "tipo_tras": "SZ",
        "com_vot": null
      },
      {
        "tipo": "COMUNE",
        "desc": "SENORBI'",
        "cod": 701,
        "ele_m": 0,
        "ele_f": 0,
        "ele_t": 4051,
        "tipo_tras": "SZ",
        "com_vot": null
      },
      {
        "tipo": "COMUNE",
        "desc": "SERDIANA",
        "cod": 711,
        "ele_m": 0,
        "ele_f": 0,
        "ele_t": 2260,
        "tipo_tras": "SZ",
        "com_vot": null
      },
      {
        "tipo": "COMUNE",
        "desc": "SERRI",
        "cod": 717,
        "ele_m": 0,
        "ele_f": 0,
        "ele_t": 525,
        "tipo_tras": "SZ",
        "com_vot": null
      },
      {
        "tipo": "COMUNE",
        "desc": "SESTU",
        "cod": 740,
        "ele_m": 0,
        "ele_f": 0,
        "ele_t": 17433,
        "tipo_tras": "SZ",
        "com_vot": null
      },
      {
        "tipo": "COMUNE",
        "desc": "SETTIMO SAN PIETRO",
        "cod": 750,
        "ele_m": 0,
        "ele_f": 0,
        "ele_t": 5876,
        "tipo_tras": "SZ",
        "com_vot": null
      },
      {
        "tipo": "COMUNE",
        "desc": "SILIQUA",
        "cod": 781,
        "ele_m": 0,
        "ele_f": 0,
        "ele_t": 3028,
        "tipo_tras": "SZ",
        "com_vot": null
      },
      {
        "tipo": "COMUNE",
        "desc": "SILIUS",
        "cod": 791,
        "ele_m": 0,
        "ele_f": 0,
        "ele_t": 892,
        "tipo_tras": "SZ",
        "com_vot": null
      },
      {
        "tipo": "COMUNE",
        "desc": "SINNAI",
        "cod": 800,
        "ele_m": 0,
        "ele_f": 0,
        "ele_t": 14722,
        "tipo_tras": "SZ",
        "com_vot": null
      },
      {
        "tipo": "COMUNE",
        "desc": "SIURGUS DONIGALA",
        "cod": 811,
        "ele_m": 0,
        "ele_f": 0,
        "ele_t": 1549,
        "tipo_tras": "SZ",
        "com_vot": null
      },
      {
        "tipo": "COMUNE",
        "desc": "SOLEMINIS",
        "cod": 821,
        "ele_m": 0,
        "ele_f": 0,
        "ele_t": 1631,
        "tipo_tras": "SZ",
        "com_vot": null
      },
      {
        "tipo": "COMUNE",
        "desc": "SUELLI",
        "cod": 831,
        "ele_m": 0,
        "ele_f": 0,
        "ele_t": 908,
        "tipo_tras": "SZ",
        "com_vot": null
      },
      {
        "tipo": "COMUNE",
        "desc": "USSANA",
        "cod": 881,
        "ele_m": 0,
        "ele_f": 0,
        "ele_t": 3459,
        "tipo_tras": "SZ",
        "com_vot": null
      },
      {
        "tipo": "COMUNE",
        "desc": "UTA",
        "cod": 900,
        "ele_m": 0,
        "ele_f": 0,
        "ele_t": 7310,
        "tipo_tras": "SZ",
        "com_vot": null
      },
      {
        "tipo": "COMUNE",
        "desc": "VALLERMOSA",
        "cod": 911,
        "ele_m": 0,
        "ele_f": 0,
        "ele_t": 1486,
        "tipo_tras": "SZ",
        "com_vot": null
      },
      {
        "tipo": "COMUNE",
        "desc": "VILLA SAN PIETRO",
        "cod": 990,
        "ele_m": 0,
        "ele_f": 0,
        "ele_t": 1760,
        "tipo_tras": "SZ",
        "com_vot": null
      },
      {
        "tipo": "COMUNE",
        "desc": "VILLANOVA TULO",
        "cod": 995,
        "ele_m": 0,
        "ele_f": 0,
        "ele_t": 874,
        "tipo_tras": "SZ",
        "com_vot": null
      },
      {
        "tipo": "COMUNE",
        "desc": "VILLAPUTZU",
        "cod": 996,
        "ele_m": 0,
        "ele_f": 0,
        "ele_t": 3864,
        "tipo_tras": "SZ",
        "com_vot": null
      },
      {
        "tipo": "COMUNE",
        "desc": "VILLASALTO",
        "cod": 998,
        "ele_m": 0,
        "ele_f": 0,
        "ele_t": 786,
        "tipo_tras": "SZ",
        "com_vot": null
      },
      {
        "tipo": "COMUNE",
        "desc": "VILLASIMIUS",
        "cod": 1030,
        "ele_m": 0,
        "ele_f": 0,
        "ele_t": 3167,
        "tipo_tras": "SZ",
        "com_vot": null
      },
      {
        "tipo": "COMUNE",
        "desc": "VILLASOR",
        "cod": 1040,
        "ele_m": 0,
        "ele_f": 0,
        "ele_t": 5564,
        "tipo_tras": "SZ",
        "com_vot": null
      },
      {
        "tipo": "COMUNE",
        "desc": "VILLASPECIOSA",
        "cod": 1050,
        "ele_m": 0,
        "ele_f": 0,
        "ele_t": 2160,
        "tipo_tras": "SZ",
        "com_vot": null
      }
    ]
  }
}